[{"StopData":[{"StopId":11188,"StopName":"府前路二段311號(示範托兒所)","ScheduleTime":"14:20","EstimateTime":"","CarInfo":"","Lon":120.186386,"Lat":22.992705,"Turn":1,"DayValue":"一,二,四,六","RecycleDate":"一,四"},{"StopId":11189,"StopName":"南島路(社會局)","ScheduleTime":"14:23","EstimateTime":"","CarInfo":"","Lon":120.186328,"Lat":22.991137,"Turn":2,"DayValue":"一,二,四,六","RecycleDate":"一,四"},{"StopId":11190,"StopName":"永華路二段6號(市議會)","ScheduleTime":"14:27","EstimateTime":"","CarInfo":"","Lon":120.185653,"Lat":22.989921,"Turn":3,"DayValue":"一,二,四,六","RecycleDate":"一,四"},{"StopId":11191,"StopName":"建平七街230號","ScheduleTime":"14:32","EstimateTime":"","CarInfo":"","Lon":120.180565,"Lat":22.988771,"Turn":4,"DayValue":"一,二,四,六","RecycleDate":"一,四"},{"StopId":11192,"StopName":"永華路二段327號","ScheduleTime":"14:34","EstimateTime":"","CarInfo":"","Lon":120.181705,"Lat":22.989616,"Turn":5,"DayValue":"一,二,四,六","RecycleDate":"一,四"},{"StopId":11193,"StopName":"建平路283號(茶行)","ScheduleTime":"14:36","EstimateTime":"","CarInfo":"","Lon":120.182252,"Lat":22.988775,"Turn":6,"DayValue":"一,二,四,六","RecycleDate":"一,四"},{"StopId":11194,"StopName":"永華二街192號","ScheduleTime":"14:38","EstimateTime":"","CarInfo":"","Lon":120.184551,"Lat":22.988707,"Turn":7,"DayValue":"一,二,四,六","RecycleDate":"一,四"},{"StopId":11195,"StopName":"建平一街路尾約180號","ScheduleTime":"14:40","EstimateTime":"","CarInfo":"","Lon":120.177483,"Lat":22.984332,"Turn":8,"DayValue":"一,二,四,六","RecycleDate":"一,四"},{"StopId":11196,"StopName":"文平路27號","ScheduleTime":"14:42","EstimateTime":"","CarInfo":"","Lon":120.177432,"Lat":22.983931,"Turn":9,"DayValue":"一,二,四,六","RecycleDate":"一,四"},{"StopId":11197,"StopName":"文平路與健康路三段路口","ScheduleTime":"14:44","EstimateTime":"","CarInfo":"","Lon":120.177348,"Lat":22.983288,"Turn":10,"DayValue":"一,二,四,六","RecycleDate":"一,四"},{"StopId":11198,"StopName":"健康路三段148號前","ScheduleTime":"14:46","EstimateTime":"","CarInfo":"","Lon":120.176502,"Lat":22.983363,"Turn":11,"DayValue":"一,二,四,六","RecycleDate":"一,四"},{"StopId":11199,"StopName":"健康路三段236號","ScheduleTime":"14:54","EstimateTime":"","CarInfo":"","Lon":120.174692,"Lat":22.983679,"Turn":12,"DayValue":"一,二,四,六","RecycleDate":"一,四"},{"StopId":11200,"StopName":"健康路三段286號","ScheduleTime":"14:55","EstimateTime":"","CarInfo":"","Lon":120.172868,"Lat":22.983989,"Turn":13,"DayValue":"一,二,四,六","RecycleDate":"一,四"},{"StopId":11201,"StopName":"健康二街66號對面","ScheduleTime":"14:57","EstimateTime":"","CarInfo":"","Lon":120.172783,"Lat":22.985511,"Turn":14,"DayValue":"一,二,四,六","RecycleDate":"一,四"},{"StopId":11202,"StopName":"郡平路151號邊","ScheduleTime":"14:59","EstimateTime":"","CarInfo":"","Lon":120.168695,"Lat":22.988977,"Turn":15,"DayValue":"一,二,四,六","RecycleDate":"一,四"},{"StopId":11203,"StopName":"育平四街2號對面","ScheduleTime":"15:01","EstimateTime":"","CarInfo":"","Lon":120.169892,"Lat":22.989505,"Turn":16,"DayValue":"一,二,四,六","RecycleDate":"一,四"},{"StopId":11204,"StopName":"健康三街209號、育平路212號(地中海)","ScheduleTime":"15:03","EstimateTime":"","CarInfo":"","Lon":120.168558,"Lat":22.989677,"Turn":17,"DayValue":"一,二,四,六","RecycleDate":"一,四"},{"StopId":11205,"StopName":"育平四街89號前","ScheduleTime":"15:05","EstimateTime":"","CarInfo":"","Lon":120.167171,"Lat":22.989852,"Turn":18,"DayValue":"一,二,四,六","RecycleDate":"一,四"},{"StopId":11206,"StopName":"建平七街825號","ScheduleTime":"15:07","EstimateTime":"","CarInfo":"","Lon":120.166062,"Lat":22.990542,"Turn":19,"DayValue":"一,二,四,六","RecycleDate":"一,四"},{"StopId":11207,"StopName":"郡平路274巷47號","ScheduleTime":"15:09","EstimateTime":"","CarInfo":"","Lon":120.16548,"Lat":22.991002,"Turn":20,"DayValue":"一,二,四,六","RecycleDate":"一,四"},{"StopId":11208,"StopName":"光州六街57號","ScheduleTime":"15:11","EstimateTime":"","CarInfo":"","Lon":120.164572,"Lat":22.991015,"Turn":21,"DayValue":"一,二,四,六","RecycleDate":"一,四"},{"StopId":11209,"StopName":"建平七街860號前","ScheduleTime":"15:13","EstimateTime":"","CarInfo":"","Lon":120.164645,"Lat":22.990591,"Turn":22,"DayValue":"一,二,四,六","RecycleDate":"一,四"},{"StopId":11210,"StopName":"郡平路274巷與平豐路236巷路口處","ScheduleTime":"15:15","EstimateTime":"","CarInfo":"","Lon":120.165242,"Lat":22.990017,"Turn":23,"DayValue":"一,二,四,六","RecycleDate":"一,四"},{"StopId":11211,"StopName":"郡平路274巷20弄18號前","ScheduleTime":"15:17","EstimateTime":"","CarInfo":"","Lon":120.165786,"Lat":22.989965,"Turn":24,"DayValue":"一,二,四,六","RecycleDate":"一,四"},{"StopId":11212,"StopName":"建平七街733號","ScheduleTime":"15:19","EstimateTime":"","CarInfo":"","Lon":120.167302,"Lat":22.990283,"Turn":25,"DayValue":"一,二,四,六","RecycleDate":"一,四"},{"StopId":11213,"StopName":"建平七街711號","ScheduleTime":"15:21","EstimateTime":"","CarInfo":"","Lon":120.167959,"Lat":22.990202,"Turn":26,"DayValue":"一,二,四,六","RecycleDate":"一,四"},{"StopId":11214,"StopName":"建平七街691號前","ScheduleTime":"15:23","EstimateTime":"","CarInfo":"","Lon":120.16857,"Lat":22.990124,"Turn":27,"DayValue":"一,二,四,六","RecycleDate":"一,四"},{"StopId":11215,"StopName":"育平五街6號(長古時代公寓)","ScheduleTime":"15:25","EstimateTime":"","CarInfo":"","Lon":120.169873,"Lat":22.990598,"Turn":28,"DayValue":"一,二,四,六","RecycleDate":"一,四"},{"StopId":11216,"StopName":"育平五街47號","ScheduleTime":"15:29","EstimateTime":"","CarInfo":"","Lon":120.168409,"Lat":22.990767,"Turn":29,"DayValue":"一,二,四,六","RecycleDate":"一,四"},{"StopId":11217,"StopName":"育平五街68號及77號","ScheduleTime":"15:30","EstimateTime":"","CarInfo":"","Lon":120.167562,"Lat":22.990866,"Turn":30,"DayValue":"一,二,四,六","RecycleDate":"一,四"},{"StopId":11218,"StopName":"華平路267號","ScheduleTime":"15:31","EstimateTime":"","CarInfo":"","Lon":120.174797,"Lat":22.989818,"Turn":31,"DayValue":"一,二,四,六","RecycleDate":"一,四"},{"StopId":11219,"StopName":"建平七街與華平路口","ScheduleTime":"15:33","EstimateTime":"","CarInfo":"","Lon":120.174747,"Lat":22.989479,"Turn":32,"DayValue":"一,二,四,六","RecycleDate":"一,四"},{"StopId":11220,"StopName":"建平七街453巷35號對面","ScheduleTime":"15:35","EstimateTime":"","CarInfo":"","Lon":120.175264,"Lat":22.988561,"Turn":33,"DayValue":"一,二,四,六","RecycleDate":"一,四"},{"StopId":11221,"StopName":"文平路187巷88弄31號對面","ScheduleTime":"15:37","EstimateTime":"","CarInfo":"","Lon":120.175728,"Lat":22.987889,"Turn":34,"DayValue":"一,二,四,六","RecycleDate":"一,四"},{"StopId":11222,"StopName":"建平五街247號對面","ScheduleTime":"15:39","EstimateTime":"","CarInfo":"","Lon":120.175793,"Lat":22.98848,"Turn":35,"DayValue":"一,二,四,六","RecycleDate":"一,四"},{"StopId":11223,"StopName":"建平七街370巷131弄77號","ScheduleTime":"15:41","EstimateTime":"","CarInfo":"","Lon":120.175921,"Lat":22.989735,"Turn":36,"DayValue":"一,二,四,六","RecycleDate":"一,四"},{"StopId":11224,"StopName":"建平七街370巷131弄49號","ScheduleTime":"15:43","EstimateTime":"","CarInfo":"","Lon":120.176733,"Lat":22.989642,"Turn":37,"DayValue":"一,二,四,六","RecycleDate":"一,四"},{"StopId":11225,"StopName":"建平七街370巷131弄1號(與建平七街口處)","ScheduleTime":"15:45","EstimateTime":"","CarInfo":"","Lon":120.177659,"Lat":22.989134,"Turn":38,"DayValue":"一,二,四,六","RecycleDate":"一,四"},{"StopId":11226,"StopName":"建平五街132巷15號","ScheduleTime":"15:47","EstimateTime":"","CarInfo":"","Lon":120.17753,"Lat":22.988148,"Turn":39,"DayValue":"一,二,四,六","RecycleDate":"一,四"},{"StopId":11227,"StopName":"建平五街172號","ScheduleTime":"15:49","EstimateTime":"","CarInfo":"","Lon":120.176995,"Lat":22.987899,"Turn":40,"DayValue":"一,二,四,六","RecycleDate":"一,四"},{"StopId":11228,"StopName":"建平五街131巷18弄32號","ScheduleTime":"15:51","EstimateTime":"","CarInfo":"","Lon":120.17671,"Lat":22.987358,"Turn":41,"DayValue":"一,二,四,六","RecycleDate":"一,四"},{"StopId":11229,"StopName":"文平路與建平五街口","ScheduleTime":"15:53","EstimateTime":"","CarInfo":"","Lon":120.177909,"Lat":22.987702,"Turn":42,"DayValue":"一,二,四,六","RecycleDate":"一,四"},{"StopId":11230,"StopName":"文平路187巷50號對面","ScheduleTime":"15:55","EstimateTime":"","CarInfo":"","Lon":120.17648,"Lat":22.98699,"Turn":43,"DayValue":"一,二,四,六","RecycleDate":"一,四"},{"StopId":11231,"StopName":"文平路187巷120號","ScheduleTime":"15:57","EstimateTime":"","CarInfo":"","Lon":120.174824,"Lat":22.987155,"Turn":44,"DayValue":"一,二,四,六","RecycleDate":"一,四"},{"StopId":11232,"StopName":"建平三街213號對面巷口","ScheduleTime":"15:59","EstimateTime":"","CarInfo":"","Lon":120.174976,"Lat":22.98587,"Turn":45,"DayValue":"一,二,四,六","RecycleDate":"一,四"},{"StopId":11233,"StopName":"建平三街178巷與建平三街200巷21弄交叉口","ScheduleTime":"16:01","EstimateTime":"","CarInfo":"","Lon":120.175586,"Lat":22.986651,"Turn":46,"DayValue":"一,二,四,六","RecycleDate":"一,四"},{"StopId":11234,"StopName":"華平路47號","ScheduleTime":"16:03","EstimateTime":"","CarInfo":"","Lon":120.174118,"Lat":22.984943,"Turn":47,"DayValue":"一,二,四,六","RecycleDate":"一,四"},{"StopId":11235,"StopName":"華平路21巷18弄48號邊","ScheduleTime":"16:05","EstimateTime":"","CarInfo":"","Lon":120.173695,"Lat":22.985315,"Turn":48,"DayValue":"一,二,四,六","RecycleDate":"一,四"},{"StopId":11236,"StopName":"華平路126號","ScheduleTime":"16:07","EstimateTime":"","CarInfo":"","Lon":120.174512,"Lat":22.986552,"Turn":49,"DayValue":"一,二,四,六","RecycleDate":"一,四"},{"StopId":11237,"StopName":"建平十七街永華六街口","ScheduleTime":"16:09","EstimateTime":"","CarInfo":"","Lon":120.177436,"Lat":22.997346,"Turn":50,"DayValue":"一,二,四,六","RecycleDate":"一,四"},{"StopId":11238,"StopName":"建平十七街159、165號前","ScheduleTime":"16:11","EstimateTime":"","CarInfo":"","Lon":120.178193,"Lat":22.997392,"Turn":51,"DayValue":"一,二,四,六","RecycleDate":"一,四"},{"StopId":11239,"StopName":"建平十七街157之1號前","ScheduleTime":"16:13","EstimateTime":"","CarInfo":"","Lon":120.178537,"Lat":22.997413,"Turn":52,"DayValue":"一,二,四,六","RecycleDate":"一,四"},{"StopId":11240,"StopName":"慶平路200號前","ScheduleTime":"16:15","EstimateTime":"","CarInfo":"","Lon":120.178675,"Lat":22.997079,"Turn":53,"DayValue":"一,二,四,六","RecycleDate":"一,四"},{"StopId":11241,"StopName":"慶平路238號旁空地","ScheduleTime":"16:17","EstimateTime":"","CarInfo":"","Lon":120.178019,"Lat":22.997038,"Turn":54,"DayValue":"一,二,四,六","RecycleDate":"一,四"},{"StopId":11242,"StopName":"慶平路394號旁空地(406號暫停蔡里長家)","ScheduleTime":"16:19","EstimateTime":"","CarInfo":"","Lon":120.176428,"Lat":22.996941,"Turn":55,"DayValue":"一,二,四,六","RecycleDate":"一,四"},{"StopId":11243,"StopName":"慶平路與華平路口","ScheduleTime":"16:21","EstimateTime":"","CarInfo":"","Lon":120.176036,"Lat":22.996916,"Turn":56,"DayValue":"一,二,四,六","RecycleDate":"一,四"},{"StopId":11244,"StopName":"慶平路257號","ScheduleTime":"16:23","EstimateTime":"","CarInfo":"","Lon":120.17682,"Lat":22.99678,"Turn":57,"DayValue":"一,二,四,六","RecycleDate":"一,四"},{"StopId":11245,"StopName":"慶平路213號旁空地(不停靠)","ScheduleTime":"16:24","EstimateTime":"","CarInfo":"","Lon":120.178112,"Lat":22.996863,"Turn":58,"DayValue":"一,二,四,六","RecycleDate":"一,四"},{"StopId":11246,"StopName":"文平路535號","ScheduleTime":"16:26","EstimateTime":"","CarInfo":"","Lon":120.179024,"Lat":22.996086,"Turn":59,"DayValue":"一,二,四,六","RecycleDate":"一,四"},{"StopId":11247,"StopName":"文平路511號","ScheduleTime":"16:28","EstimateTime":"","CarInfo":"","Lon":120.178957,"Lat":22.995566,"Turn":60,"DayValue":"一,二,四,六","RecycleDate":"一,四"},{"StopId":11248,"StopName":"建平12街148巷16號","ScheduleTime":"16:30","EstimateTime":"","CarInfo":"","Lon":120.178624,"Lat":22.996017,"Turn":61,"DayValue":"一,二,四,六","RecycleDate":"一,四"},{"StopId":11249,"StopName":"永華六街279巷與建平十二街386巷口","ScheduleTime":"16:33","EstimateTime":"","CarInfo":"","Lon":120.17684,"Lat":22.996402,"Turn":62,"DayValue":"一,二,四,六","RecycleDate":"一,四"},{"StopId":11250,"StopName":"建平12街396巷18號","ScheduleTime":"16:35","EstimateTime":"","CarInfo":"","Lon":120.176339,"Lat":22.996273,"Turn":63,"DayValue":"一,二,四,六","RecycleDate":"一,四"},{"StopId":11251,"StopName":"建平十二街396巷2號前","ScheduleTime":"16:37","EstimateTime":"","CarInfo":"","Lon":120.176401,"Lat":22.995703,"Turn":64,"DayValue":"一,二,四,六","RecycleDate":"一,四"},{"StopId":11252,"StopName":"永華六街與建平十二街口","ScheduleTime":"16:39","EstimateTime":"","CarInfo":"","Lon":120.177194,"Lat":22.995609,"Turn":65,"DayValue":"一,二,四,六","RecycleDate":"一,四"},{"StopId":11253,"StopName":"建平12街135、145號","ScheduleTime":"16:42","EstimateTime":"","CarInfo":"","Lon":120.177913,"Lat":22.995524,"Turn":66,"DayValue":"一,二,四,六","RecycleDate":"一,四"},{"StopId":11254,"StopName":"文平路與建平十一街口","ScheduleTime":"16:44","EstimateTime":"","CarInfo":"","Lon":120.178858,"Lat":22.995028,"Turn":67,"DayValue":"一,二,四,六","RecycleDate":"一,四"},{"StopId":11255,"StopName":"建平十一街260號","ScheduleTime":"16:46","EstimateTime":"","CarInfo":"","Lon":120.177867,"Lat":22.99515,"Turn":68,"DayValue":"一,二,四,六","RecycleDate":"一,四"},{"StopId":11256,"StopName":"永華六街建平十一街口","ScheduleTime":"16:49","EstimateTime":"","CarInfo":"","Lon":120.177128,"Lat":22.995237,"Turn":69,"DayValue":"一,二,四,六","RecycleDate":"一,四"},{"StopId":11257,"StopName":"華平路與建平十一街口","ScheduleTime":"16:51","EstimateTime":"","CarInfo":"","Lon":120.175791,"Lat":22.995389,"Turn":70,"DayValue":"一,二,四,六","RecycleDate":"一,四"},{"StopId":11258,"StopName":"華平路650號","ScheduleTime":"16:53","EstimateTime":"","CarInfo":"","Lon":120.175812,"Lat":22.995713,"Turn":71,"DayValue":"一,二,四,六","RecycleDate":"一,四"},{"StopId":11259,"StopName":"慶平路412號","ScheduleTime":"16:55","EstimateTime":"","CarInfo":"","Lon":120.175591,"Lat":22.996938,"Turn":72,"DayValue":"一,二,四,六","RecycleDate":"一,四"},{"StopId":11260,"StopName":"慶平路446號","ScheduleTime":"16:56","EstimateTime":"","CarInfo":"","Lon":120.174887,"Lat":22.997011,"Turn":73,"DayValue":"一,二,四,六","RecycleDate":"一,四"},{"StopId":11261,"StopName":"建平17街243號","ScheduleTime":"16:57","EstimateTime":"","CarInfo":"","Lon":120.175449,"Lat":22.997221,"Turn":74,"DayValue":"一,二,四,六","RecycleDate":"一,四"}],"CarData":[],"RouteId":337,"RouteName":"安平區-4(下午)","RouteInfo":"府前路二段311號(示範托兒所)~建平17街243號","IsWork":true}]