[{"StopData":[{"StopId":13182,"StopName":"仁義路222號(聖人骨科斜對面)","ScheduleTime":"16:39","EstimateTime":"","CarInfo":"","Lon":120.2592461,"Lat":22.9691122,"Turn":1,"DayValue":"一,二,四,六","RecycleDate":"二,六"},{"StopId":13183,"StopName":"保安路一段7號","ScheduleTime":"16:45","EstimateTime":"","CarInfo":"","Lon":120.2244473,"Lat":22.9234392,"Turn":2,"DayValue":"一,二,四,六","RecycleDate":"二,六"},{"StopId":13184,"StopName":"保安路一段80號","ScheduleTime":"16:45","EstimateTime":"","CarInfo":"","Lon":120.226521,"Lat":22.926638,"Turn":3,"DayValue":"一,二,四,六","RecycleDate":"二,六"},{"StopId":13185,"StopName":"保安路一段105巷19號","ScheduleTime":"16:42","EstimateTime":"","CarInfo":"","Lon":120.2303478,"Lat":22.9312484,"Turn":4,"DayValue":"一,二,四,六","RecycleDate":"二,六"},{"StopId":13186,"StopName":"保安路二段547號","ScheduleTime":"16:48","EstimateTime":"","CarInfo":"","Lon":120.24529,"Lat":22.9376385,"Turn":5,"DayValue":"一,二,四,六","RecycleDate":"二,六"},{"StopId":13187,"StopName":"田厝二街15號","ScheduleTime":"16:48","EstimateTime":"","CarInfo":"","Lon":120.24401,"Lat":22.9376089,"Turn":6,"DayValue":"一,二,四,六","RecycleDate":"二,六"},{"StopId":13188,"StopName":"田厝二街56號","ScheduleTime":"16:48","EstimateTime":"","CarInfo":"","Lon":120.243479,"Lat":22.9381226,"Turn":7,"DayValue":"一,二,四,六","RecycleDate":"二,六"},{"StopId":13189,"StopName":"田厝二街88號(水明殿)","ScheduleTime":"16:48","EstimateTime":"","CarInfo":"","Lon":120.2427038,"Lat":22.9386438,"Turn":8,"DayValue":"一,二,四,六","RecycleDate":"二,六"},{"StopId":13190,"StopName":"田厝二街131號","ScheduleTime":"16:48","EstimateTime":"","CarInfo":"","Lon":120.2410874,"Lat":22.938801,"Turn":9,"DayValue":"一,二,四,六","RecycleDate":"二,六"},{"StopId":13191,"StopName":"田厝一街216巷1號","ScheduleTime":"16:48","EstimateTime":"","CarInfo":"","Lon":120.2423416,"Lat":22.9392846,"Turn":10,"DayValue":"一,二,四,六","RecycleDate":"二,六"},{"StopId":13192,"StopName":"田厝一街202巷1號","ScheduleTime":"16:48","EstimateTime":"","CarInfo":"","Lon":120.2425554,"Lat":22.9397688,"Turn":11,"DayValue":"一,二,四,六","RecycleDate":"二,六"},{"StopId":13193,"StopName":"田厝二街64巷31號","ScheduleTime":"16:48","EstimateTime":"","CarInfo":"","Lon":120.2436229,"Lat":22.9393953,"Turn":12,"DayValue":"一,二,四,六","RecycleDate":"二,六"},{"StopId":13194,"StopName":"田厝二街64巷19弄2號","ScheduleTime":"16:48","EstimateTime":"","CarInfo":"","Lon":120.2436143,"Lat":22.9387151,"Turn":13,"DayValue":"一,二,四,六","RecycleDate":"二,六"},{"StopId":13195,"StopName":"保安路二段481號(田厝活動中心)","ScheduleTime":"16:48","EstimateTime":"","CarInfo":"","Lon":120.243617,"Lat":22.937119,"Turn":14,"DayValue":"一,二,四,六","RecycleDate":"二,六"},{"StopId":13196,"StopName":"田厝三街28號(35巷口)","ScheduleTime":"16:48","EstimateTime":"","CarInfo":"","Lon":120.2436971,"Lat":22.9360242,"Turn":15,"DayValue":"一,二,四,六","RecycleDate":"二,六"},{"StopId":13197,"StopName":"田厝三街70巷19號(西安宮前)","ScheduleTime":"16:48","EstimateTime":"","CarInfo":"","Lon":120.2447915,"Lat":22.9356152,"Turn":16,"DayValue":"一,二,四,六","RecycleDate":"二,六"},{"StopId":13198,"StopName":"田厝三街70巷5號","ScheduleTime":"16:48","EstimateTime":"","CarInfo":"","Lon":120.2445983,"Lat":22.9357919,"Turn":17,"DayValue":"一,二,四,六","RecycleDate":"二,六"},{"StopId":13199,"StopName":"田厝三街91號","ScheduleTime":"17:12","EstimateTime":"","CarInfo":"","Lon":120.2450009,"Lat":22.936265,"Turn":18,"DayValue":"一,二,四,六","RecycleDate":"二,六"},{"StopId":13200,"StopName":"田厝三街98巷1號","ScheduleTime":"17:17","EstimateTime":"","CarInfo":"","Lon":120.2457348,"Lat":22.936355,"Turn":19,"DayValue":"一,二,四,六","RecycleDate":"二,六"},{"StopId":13201,"StopName":"田厝三街118號","ScheduleTime":"17:17","EstimateTime":"","CarInfo":"","Lon":120.2455126,"Lat":22.9373018,"Turn":20,"DayValue":"一,二,四,六","RecycleDate":"二,六"},{"StopId":13202,"StopName":"三甲里22號之2","ScheduleTime":"17:17","EstimateTime":"","CarInfo":"","Lon":120.2393043,"Lat":22.9344115,"Turn":21,"DayValue":"一,二,四,六","RecycleDate":"二,六"},{"StopId":13203,"StopName":"三甲里20號之2","ScheduleTime":"17:17","EstimateTime":"","CarInfo":"","Lon":120.2398059,"Lat":22.9340879,"Turn":22,"DayValue":"一,二,四,六","RecycleDate":"二,六"},{"StopId":13204,"StopName":"三甲里26號之19","ScheduleTime":"17:17","EstimateTime":"","CarInfo":"","Lon":120.2382224,"Lat":22.9312271,"Turn":23,"DayValue":"一,二,四,六","RecycleDate":"二,六"},{"StopId":13205,"StopName":"三甲里47號之4","ScheduleTime":"17:17","EstimateTime":"","CarInfo":"","Lon":120.2386032,"Lat":22.9299351,"Turn":24,"DayValue":"一,二,四,六","RecycleDate":"二,六"},{"StopId":13206,"StopName":"三甲里47號之1","ScheduleTime":"17:17","EstimateTime":"","CarInfo":"","Lon":120.2390189,"Lat":22.9291495,"Turn":25,"DayValue":"一,二,四,六","RecycleDate":"二,六"},{"StopId":13207,"StopName":"三甲里81號","ScheduleTime":"17:17","EstimateTime":"","CarInfo":"","Lon":120.2381349,"Lat":22.9272799,"Turn":26,"DayValue":"一,二,四,六","RecycleDate":"二,六"},{"StopId":13208,"StopName":"三甲里48號之25","ScheduleTime":"17:17","EstimateTime":"","CarInfo":"","Lon":120.2392121,"Lat":22.9265632,"Turn":27,"DayValue":"一,二,四,六","RecycleDate":"二,六"},{"StopId":13209,"StopName":"三甲里37號之7","ScheduleTime":"17:17","EstimateTime":"","CarInfo":"","Lon":120.2370771,"Lat":22.9309058,"Turn":28,"DayValue":"一,二,四,六","RecycleDate":"二,六"},{"StopId":13210,"StopName":"三甲里11號之5(三爺宮)","ScheduleTime":"17:17","EstimateTime":"","CarInfo":"","Lon":120.2365685,"Lat":22.9326774,"Turn":29,"DayValue":"一,二,四,六","RecycleDate":"二,六"},{"StopId":13211,"StopName":"三甲里67號","ScheduleTime":"17:17","EstimateTime":"","CarInfo":"","Lon":120.2334807,"Lat":22.9318892,"Turn":30,"DayValue":"一,二,四,六","RecycleDate":"二,六"},{"StopId":13212,"StopName":"保安路一段135號","ScheduleTime":"17:17","EstimateTime":"","CarInfo":"","Lon":120.2314615,"Lat":22.9311448,"Turn":31,"DayValue":"一,二,四,六","RecycleDate":"二,六"},{"StopId":13213,"StopName":"文賢路一段620號(文賢一街)","ScheduleTime":"17:17","EstimateTime":"","CarInfo":"","Lon":120.2310447,"Lat":22.9298296,"Turn":32,"DayValue":"一,二,四,六","RecycleDate":"二,六"},{"StopId":13214,"StopName":"文賢路一段529巷2號(保安車站)","ScheduleTime":"17:41","EstimateTime":"","CarInfo":"","Lon":120.2308841,"Lat":22.9325795,"Turn":33,"DayValue":"一,二,四,六","RecycleDate":"二,六"},{"StopId":13215,"StopName":"文賢路一段519號","ScheduleTime":"17:43","EstimateTime":"","CarInfo":"","Lon":120.2304992,"Lat":22.9333132,"Turn":34,"DayValue":"一,二,四,六","RecycleDate":"二,六"},{"StopId":13216,"StopName":"文賢路一段556號","ScheduleTime":"17:43","EstimateTime":"","CarInfo":"","Lon":120.2309538,"Lat":22.9314229,"Turn":35,"DayValue":"一,二,四,六","RecycleDate":"二,六"},{"StopId":13217,"StopName":"文賢路一段702號","ScheduleTime":"17:43","EstimateTime":"","CarInfo":"","Lon":120.2322319,"Lat":22.9273883,"Turn":36,"DayValue":"一,二,四,六","RecycleDate":"二,六"},{"StopId":13218,"StopName":"文賢路一段830號","ScheduleTime":"17:43","EstimateTime":"","CarInfo":"","Lon":120.2343784,"Lat":22.9249836,"Turn":37,"DayValue":"一,二,四,六","RecycleDate":"二,六"},{"StopId":13219,"StopName":"文賢路一段858號","ScheduleTime":"17:43","EstimateTime":"","CarInfo":"","Lon":120.2348272,"Lat":22.924195,"Turn":38,"DayValue":"一,二,四,六","RecycleDate":"二,六"},{"StopId":13220,"StopName":"文賢路一段860號(保安宮)","ScheduleTime":"17:43","EstimateTime":"","CarInfo":"","Lon":120.2348429,"Lat":22.9238767,"Turn":39,"DayValue":"一,二,四,六","RecycleDate":"二,六"},{"StopId":13221,"StopName":"文賢路二段20號","ScheduleTime":"17:43","EstimateTime":"","CarInfo":"","Lon":120.2367916,"Lat":22.921751,"Turn":40,"DayValue":"一,二,四,六","RecycleDate":"二,六"},{"StopId":13222,"StopName":"中正路一段210巷12號","ScheduleTime":"17:43","EstimateTime":"","CarInfo":"","Lon":120.2361404,"Lat":22.9210835,"Turn":41,"DayValue":"一,二,四,六","RecycleDate":"二,六"},{"StopId":13223,"StopName":"文賢路二段18巷13號","ScheduleTime":"18:04","EstimateTime":"","CarInfo":"","Lon":120.2364273,"Lat":22.9214977,"Turn":42,"DayValue":"一,二,四,六","RecycleDate":"二,六"},{"StopId":13224,"StopName":"文賢路二段15巷26號","ScheduleTime":"18:10","EstimateTime":"","CarInfo":"","Lon":120.2381013,"Lat":22.9226476,"Turn":43,"DayValue":"一,二,四,六","RecycleDate":"二,六"},{"StopId":13225,"StopName":"文賢路二段15巷52號","ScheduleTime":"18:10","EstimateTime":"","CarInfo":"","Lon":120.2386933,"Lat":22.9230071,"Turn":44,"DayValue":"一,二,四,六","RecycleDate":"二,六"},{"StopId":13226,"StopName":"三甲里57之11號","ScheduleTime":"18:10","EstimateTime":"","CarInfo":"","Lon":120.2436323,"Lat":22.9281194,"Turn":45,"DayValue":"一,二,四,六","RecycleDate":"二,六"},{"StopId":13227,"StopName":"中正路一段229-2號","ScheduleTime":"18:10","EstimateTime":"","CarInfo":"","Lon":120.2373161,"Lat":22.9229636,"Turn":46,"DayValue":"一,二,四,六","RecycleDate":"二,六"},{"StopId":13228,"StopName":"中正路一段209號","ScheduleTime":"18:14","EstimateTime":"","CarInfo":"","Lon":120.2363824,"Lat":22.9223128,"Turn":47,"DayValue":"一,二,四,六","RecycleDate":"二,六"},{"StopId":13229,"StopName":"中洲93號之26","ScheduleTime":"19:13","EstimateTime":"","CarInfo":"","Lon":120.2498653,"Lat":22.9091035,"Turn":48,"DayValue":"一,二,四,六","RecycleDate":"二,六"},{"StopId":13230,"StopName":"中洲93號之1","ScheduleTime":"19:20","EstimateTime":"","CarInfo":"","Lon":120.2499861,"Lat":22.908723,"Turn":49,"DayValue":"一,二,四,六","RecycleDate":"二,六"},{"StopId":13231,"StopName":"中洲73號","ScheduleTime":"19:20","EstimateTime":"","CarInfo":"","Lon":120.2508605,"Lat":22.9087477,"Turn":50,"DayValue":"一,二,四,六","RecycleDate":"二,六"},{"StopId":13232,"StopName":"中洲76-28號巷口","ScheduleTime":"19:20","EstimateTime":"","CarInfo":"","Lon":120.2506673,"Lat":22.9094691,"Turn":51,"DayValue":"一,二,四,六","RecycleDate":"二,六"},{"StopId":13233,"StopName":"中洲155號(中洲市場)","ScheduleTime":"19:20","EstimateTime":"","CarInfo":"","Lon":120.2506148,"Lat":22.9069951,"Turn":52,"DayValue":"一,二,四,六","RecycleDate":"二,六"},{"StopId":13234,"StopName":"中洲201號之1","ScheduleTime":"19:20","EstimateTime":"","CarInfo":"","Lon":120.2504287,"Lat":22.9064774,"Turn":53,"DayValue":"一,二,四,六","RecycleDate":"二,六"},{"StopId":13235,"StopName":"中洲144號","ScheduleTime":"19:20","EstimateTime":"","CarInfo":"","Lon":120.2499839,"Lat":22.9061649,"Turn":54,"DayValue":"一,二,四,六","RecycleDate":"二,六"},{"StopId":13236,"StopName":"中洲140號之4","ScheduleTime":"19:20","EstimateTime":"","CarInfo":"","Lon":120.2497619,"Lat":22.9059874,"Turn":55,"DayValue":"一,二,四,六","RecycleDate":"二,六"},{"StopId":13237,"StopName":"中洲140號","ScheduleTime":"19:31","EstimateTime":"","CarInfo":"","Lon":120.2495812,"Lat":22.905689,"Turn":56,"DayValue":"一,二,四,六","RecycleDate":"二,六"},{"StopId":13238,"StopName":"中洲224號之6","ScheduleTime":"19:38","EstimateTime":"","CarInfo":"","Lon":120.2502812,"Lat":22.9053557,"Turn":57,"DayValue":"一,二,四,六","RecycleDate":"二,六"},{"StopId":13239,"StopName":"中洲240號","ScheduleTime":"19:38","EstimateTime":"","CarInfo":"","Lon":120.2512629,"Lat":22.9056447,"Turn":58,"DayValue":"一,二,四,六","RecycleDate":"二,六"},{"StopId":13240,"StopName":"中洲250號之26","ScheduleTime":"19:38","EstimateTime":"","CarInfo":"","Lon":120.2523197,"Lat":22.9035594,"Turn":59,"DayValue":"一,二,四,六","RecycleDate":"二,六"},{"StopId":13241,"StopName":"中洲253號之6","ScheduleTime":"19:38","EstimateTime":"","CarInfo":"","Lon":120.2516974,"Lat":22.9058498,"Turn":60,"DayValue":"一,二,四,六","RecycleDate":"二,六"},{"StopId":13242,"StopName":"中洲48號之1","ScheduleTime":"19:38","EstimateTime":"","CarInfo":"","Lon":120.2511448,"Lat":22.907836,"Turn":61,"DayValue":"一,二,四,六","RecycleDate":"二,六"},{"StopId":13243,"StopName":"中洲345號之1","ScheduleTime":"19:38","EstimateTime":"","CarInfo":"","Lon":120.2524297,"Lat":22.9073569,"Turn":62,"DayValue":"一,二,四,六","RecycleDate":"二,六"},{"StopId":13244,"StopName":"中洲372號","ScheduleTime":"19:38","EstimateTime":"","CarInfo":"","Lon":120.253583,"Lat":22.9071444,"Turn":63,"DayValue":"一,二,四,六","RecycleDate":"二,六"},{"StopId":13245,"StopName":"中洲374號之2","ScheduleTime":"19:38","EstimateTime":"","CarInfo":"","Lon":120.2534328,"Lat":22.906507,"Turn":64,"DayValue":"一,二,四,六","RecycleDate":"二,六"},{"StopId":13246,"StopName":"中洲349號之3","ScheduleTime":"19:38","EstimateTime":"","CarInfo":"","Lon":120.2527006,"Lat":22.9062352,"Turn":65,"DayValue":"一,二,四,六","RecycleDate":"二,六"},{"StopId":13247,"StopName":"中洲298號之1(中洲車站)","ScheduleTime":"19:38","EstimateTime":"","CarInfo":"","Lon":120.2528523,"Lat":22.9045862,"Turn":66,"DayValue":"一,二,四,六","RecycleDate":"二,六"},{"StopId":13248,"StopName":"中洲318號之6","ScheduleTime":"19:38","EstimateTime":"","CarInfo":"","Lon":120.2528454,"Lat":22.9050666,"Turn":67,"DayValue":"一,二,四,六","RecycleDate":"二,六"},{"StopId":13249,"StopName":"中洲385號之39","ScheduleTime":"19:38","EstimateTime":"","CarInfo":"","Lon":120.2538915,"Lat":22.9078832,"Turn":68,"DayValue":"一,二,四,六","RecycleDate":"二,六"},{"StopId":13250,"StopName":"中洲1號之123","ScheduleTime":"19:38","EstimateTime":"","CarInfo":"","Lon":120.2554018,"Lat":22.9098454,"Turn":69,"DayValue":"一,二,四,六","RecycleDate":"二,六"},{"StopId":13251,"StopName":"中洲5號之25","ScheduleTime":"19:38","EstimateTime":"","CarInfo":"","Lon":120.2534455,"Lat":22.9091278,"Turn":70,"DayValue":"一,二,四,六","RecycleDate":"二,六"},{"StopId":13252,"StopName":"中洲28號之12","ScheduleTime":"19:56","EstimateTime":"","CarInfo":"","Lon":120.2514481,"Lat":22.9089783,"Turn":71,"DayValue":"一,二,四,六","RecycleDate":"二,六"},{"StopId":13253,"StopName":"中洲41號之2","ScheduleTime":"20:00","EstimateTime":"","CarInfo":"","Lon":120.2517215,"Lat":22.9085303,"Turn":72,"DayValue":"一,二,四,六","RecycleDate":"二,六"},{"StopId":13254,"StopName":"中洲385號之52","ScheduleTime":"20:00","EstimateTime":"","CarInfo":"","Lon":120.2524619,"Lat":22.9080536,"Turn":73,"DayValue":"一,二,四,六","RecycleDate":"二,六"},{"StopId":13255,"StopName":"中洲385號之29","ScheduleTime":"20:00","EstimateTime":"","CarInfo":"","Lon":120.2531861,"Lat":22.9081499,"Turn":74,"DayValue":"一,二,四,六","RecycleDate":"二,六"},{"StopId":13256,"StopName":"中洲5號之56","ScheduleTime":"20:00","EstimateTime":"","CarInfo":"","Lon":120.253763,"Lat":22.9083632,"Turn":75,"DayValue":"一,二,四,六","RecycleDate":"二,六"},{"StopId":13257,"StopName":"中洲53號(中洲教會)","ScheduleTime":"20:00","EstimateTime":"","CarInfo":"","Lon":120.2509345,"Lat":22.9079766,"Turn":76,"DayValue":"一,二,四,六","RecycleDate":"二,六"},{"StopId":13258,"StopName":"中洲里67號(保生宮)","ScheduleTime":"20:00","EstimateTime":"","CarInfo":"","Lon":120.250629,"Lat":22.9078984,"Turn":77,"DayValue":"一,二,四,六","RecycleDate":"二,六"},{"StopId":13259,"StopName":"中洲100號","ScheduleTime":"20:00","EstimateTime":"","CarInfo":"","Lon":120.2497538,"Lat":22.9075711,"Turn":78,"DayValue":"一,二,四,六","RecycleDate":"二,六"},{"StopId":13260,"StopName":"中洲116號之2(天后宮)","ScheduleTime":"20:00","EstimateTime":"","CarInfo":"","Lon":120.2491609,"Lat":22.9074417,"Turn":79,"DayValue":"一,二,四,六","RecycleDate":"二,六"},{"StopId":13261,"StopName":"中洲120號之2","ScheduleTime":"20:00","EstimateTime":"","CarInfo":"","Lon":120.2488595,"Lat":22.9073814,"Turn":80,"DayValue":"一,二,四,六","RecycleDate":"二,六"},{"StopId":13262,"StopName":"中洲125-3號巷口","ScheduleTime":"20:00","EstimateTime":"","CarInfo":"","Lon":120.247674,"Lat":22.9071961,"Turn":81,"DayValue":"一,二,四,六","RecycleDate":"二,六"},{"StopId":13263,"StopName":"中洲76-61號巷口","ScheduleTime":"20:00","EstimateTime":"","CarInfo":"","Lon":120.2487684,"Lat":22.907967,"Turn":82,"DayValue":"一,二,四,六","RecycleDate":"二,六"}],"CarData":[{"CarNo":"AAQ-007","Angle":243,"Lon":120.233642,"Lat":22.931949}],"RouteId":320,"RouteName":"仁德-03","RouteInfo":"仁義路222號(聖人骨科斜對面)~中洲76-61號巷口","IsWork":true}]