[{"StopData":[{"StopId":3555,"StopName":"白河小鎮中山路449巷105弄21號","ScheduleTime":"16:30","EstimateTime":"","CarInfo":"","Lon":120.4184688,"Lat":23.357251,"Turn":1,"DayValue":"三","RecycleDate":""},{"StopId":3556,"StopName":"大竹里189-6號","ScheduleTime":"16:38","EstimateTime":"","CarInfo":"","Lon":120.4069989,"Lat":23.3676357,"Turn":2,"DayValue":"三","RecycleDate":""},{"StopId":3557,"StopName":"大竹里140號","ScheduleTime":"16:45","EstimateTime":"","CarInfo":"","Lon":120.4100802,"Lat":23.3677697,"Turn":3,"DayValue":"三","RecycleDate":""},{"StopId":3558,"StopName":"觀音廟大排竹120-16號","ScheduleTime":"16:50","EstimateTime":"","CarInfo":"","Lon":120.4127284,"Lat":23.3645275,"Turn":4,"DayValue":"三","RecycleDate":""},{"StopId":3559,"StopName":"六順宮大排竹173號","ScheduleTime":"16:55","EstimateTime":"","CarInfo":"","Lon":120.4095086,"Lat":23.3690648,"Turn":5,"DayValue":"三","RecycleDate":""},{"StopId":3560,"StopName":"靈感公大排竹59號","ScheduleTime":"17:05","EstimateTime":"","CarInfo":"","Lon":120.4112531,"Lat":23.3689654,"Turn":6,"DayValue":"三","RecycleDate":""},{"StopId":3561,"StopName":"玉豐下庄順安宮海豐厝109-1號","ScheduleTime":"17:11","EstimateTime":"","CarInfo":"","Lon":120.4138183,"Lat":23.3759903,"Turn":7,"DayValue":"三","RecycleDate":""},{"StopId":3562,"StopName":"太豐宮海豐厝130號","ScheduleTime":"17:17","EstimateTime":"","CarInfo":"","Lon":120.4155821,"Lat":23.3764423,"Turn":8,"DayValue":"三","RecycleDate":""},{"StopId":3563,"StopName":"澎祖廟口海豐厝92-25號","ScheduleTime":"17:23","EstimateTime":"","CarInfo":"","Lon":120.4135275,"Lat":23.3780928,"Turn":9,"DayValue":"三","RecycleDate":""},{"StopId":3564,"StopName":"玉豐國小路口玉豐里85號","ScheduleTime":"17:28","EstimateTime":"","CarInfo":"","Lon":120.416508,"Lat":23.3793732,"Turn":10,"DayValue":"三","RecycleDate":""},{"StopId":3565,"StopName":"玉豐碾米廠玉豐里72號","ScheduleTime":"17:34","EstimateTime":"","CarInfo":"","Lon":120.4169453,"Lat":23.378503,"Turn":11,"DayValue":"三","RecycleDate":""},{"StopId":3566,"StopName":"頂山腳頂山腳20號","ScheduleTime":"17:35","EstimateTime":"","CarInfo":"","Lon":120.4143954,"Lat":23.3869717,"Turn":12,"DayValue":"三","RecycleDate":""},{"StopId":3567,"StopName":"詔安大廟口詔安厝74-2號","ScheduleTime":"17:39","EstimateTime":"","CarInfo":"","Lon":120.4122978,"Lat":23.3929457,"Turn":13,"DayValue":"三","RecycleDate":""},{"StopId":3568,"StopName":"天安宮  詔安厝24-15號","ScheduleTime":"17:46","EstimateTime":"","CarInfo":"","Lon":120.4115275,"Lat":23.3958642,"Turn":14,"DayValue":"三","RecycleDate":""},{"StopId":3569,"StopName":"山子腳32-3號","ScheduleTime":"17:57","EstimateTime":"","CarInfo":"","Lon":120.4044141,"Lat":23.3970436,"Turn":15,"DayValue":"三","RecycleDate":""},{"StopId":3570,"StopName":"大安宮路口蓮潭里29-1號","ScheduleTime":"18:19","EstimateTime":"","CarInfo":"","Lon":120.4006357,"Lat":23.3988848,"Turn":16,"DayValue":"三","RecycleDate":""},{"StopId":3571,"StopName":"大山宮山子腳57號","ScheduleTime":"18:25","EstimateTime":"","CarInfo":"","Lon":120.4047531,"Lat":23.398623,"Turn":17,"DayValue":"三","RecycleDate":""},{"StopId":3572,"StopName":"北埔3號","ScheduleTime":"18:30","EstimateTime":"","CarInfo":"","Lon":120.4084109,"Lat":23.40867,"Turn":18,"DayValue":"三","RecycleDate":""},{"StopId":3573,"StopName":"廣安里小南海路口廣安里27-7號","ScheduleTime":"18:45","EstimateTime":"","CarInfo":"","Lon":120.4034653,"Lat":23.3907281,"Turn":19,"DayValue":"三","RecycleDate":""},{"StopId":3574,"StopName":"水池枋子林58號","ScheduleTime":"18:47","EstimateTime":"","CarInfo":"","Lon":120.4027692,"Lat":23.3879318,"Turn":20,"DayValue":"三","RecycleDate":""},{"StopId":3575,"StopName":"水利大埤橋頭埤斗子8-5號","ScheduleTime":"18:52","EstimateTime":"","CarInfo":"","Lon":120.4089053,"Lat":23.3881162,"Turn":21,"DayValue":"三","RecycleDate":""}],"CarData":[],"RouteId":95,"RouteName":"白河-5-3","RouteInfo":"白河小鎮中山路449巷105弄21號~水利大埤橋頭埤斗子8-5號","IsWork":false}]