[{"StopData":[{"StopId":7052,"StopName":"大通一街26號","ScheduleTime":"16:51","EstimateTime":"","CarInfo":"","Lon":120.2969795,"Lat":22.9682115,"Turn":1,"DayValue":"一,二,四,六","RecycleDate":"一,四"},{"StopId":7053,"StopName":"大通一街105號","ScheduleTime":"16:52","EstimateTime":"","CarInfo":"","Lon":120.2969731,"Lat":22.9688459,"Turn":2,"DayValue":"一,二,四,六","RecycleDate":"一,四"},{"StopId":7054,"StopName":"和平二街13號（忠順府）","ScheduleTime":"16:53","EstimateTime":"","CarInfo":"","Lon":120.2968824,"Lat":22.969444,"Turn":3,"DayValue":"一,二,四,六","RecycleDate":"一,四"},{"StopId":7055,"StopName":"和平一街口","ScheduleTime":"16:54","EstimateTime":"","CarInfo":"","Lon":120.2963528,"Lat":22.9694739,"Turn":4,"DayValue":"一,二,四,六","RecycleDate":"一,四"},{"StopId":7056,"StopName":"和平三街32號","ScheduleTime":"16:55","EstimateTime":"","CarInfo":"","Lon":120.2955269,"Lat":22.9688438,"Turn":5,"DayValue":"一,二,四,六","RecycleDate":"一,四"},{"StopId":7057,"StopName":"和平北街40號","ScheduleTime":"16:56","EstimateTime":"","CarInfo":"","Lon":120.2963815,"Lat":22.9681185,"Turn":6,"DayValue":"一,二,四,六","RecycleDate":"一,四"},{"StopId":7058,"StopName":"大通路100巷口","ScheduleTime":"16:57","EstimateTime":"","CarInfo":"","Lon":120.2938007,"Lat":22.9680037,"Turn":7,"DayValue":"一,二,四,六","RecycleDate":"一,四"},{"StopId":7059,"StopName":"大通路116號","ScheduleTime":"16:58","EstimateTime":"","CarInfo":"","Lon":120.2935064,"Lat":22.9679479,"Turn":8,"DayValue":"一,二,四,六","RecycleDate":"一,四"},{"StopId":7060,"StopName":"大通路150號","ScheduleTime":"16:59","EstimateTime":"","CarInfo":"","Lon":120.2928404,"Lat":22.9681165,"Turn":9,"DayValue":"一,二,四,六","RecycleDate":"一,四"},{"StopId":7061,"StopName":"民族北街21號","ScheduleTime":"17:00","EstimateTime":"","CarInfo":"","Lon":120.2922296,"Lat":22.9678472,"Turn":10,"DayValue":"一,二,四,六","RecycleDate":"一,四"},{"StopId":7062,"StopName":"中山六街9號","ScheduleTime":"17:01","EstimateTime":"","CarInfo":"","Lon":120.2930086,"Lat":22.9677076,"Turn":11,"DayValue":"一,二,四,六","RecycleDate":"一,四"},{"StopId":7063,"StopName":"中正北路一段3巷20號","ScheduleTime":"17:02","EstimateTime":"","CarInfo":"","Lon":120.2934657,"Lat":22.9676089,"Turn":12,"DayValue":"一,二,四,六","RecycleDate":"一,四"},{"StopId":7064,"StopName":"民族北街（大佳加油站）","ScheduleTime":"17:10","EstimateTime":"","CarInfo":"","Lon":120.2962401,"Lat":22.9669845,"Turn":13,"DayValue":"一,二,四,六","RecycleDate":"一,四"},{"StopId":7065,"StopName":"民族北街17巷38弄口","ScheduleTime":"17:12","EstimateTime":"","CarInfo":"","Lon":120.2912783,"Lat":22.9676791,"Turn":14,"DayValue":"一,二,四,六","RecycleDate":"一,四"},{"StopId":7066,"StopName":"民族北街17巷45號","ScheduleTime":"17:14","EstimateTime":"","CarInfo":"","Lon":120.2910942,"Lat":22.9676918,"Turn":15,"DayValue":"一,二,四,六","RecycleDate":"一,四"},{"StopId":7067,"StopName":"國光街89巷口","ScheduleTime":"17:16","EstimateTime":"","CarInfo":"","Lon":120.2905219,"Lat":22.9682171,"Turn":16,"DayValue":"一,二,四,六","RecycleDate":"一,四"},{"StopId":7068,"StopName":"民族一街46號","ScheduleTime":"17:18","EstimateTime":"","CarInfo":"","Lon":120.290968,"Lat":22.9689226,"Turn":17,"DayValue":"一,二,四,六","RecycleDate":"一,四"},{"StopId":7069,"StopName":"民族一街13號","ScheduleTime":"17:20","EstimateTime":"","CarInfo":"","Lon":120.2710472,"Lat":23.0032556,"Turn":18,"DayValue":"一,二,四,六","RecycleDate":"一,四"},{"StopId":7070,"StopName":"民族北街55號","ScheduleTime":"17:22","EstimateTime":"","CarInfo":"","Lon":120.292318,"Lat":22.9682843,"Turn":19,"DayValue":"一,二,四,六","RecycleDate":"一,四"},{"StopId":7071,"StopName":"民族北街82號","ScheduleTime":"17:23","EstimateTime":"","CarInfo":"","Lon":120.2924548,"Lat":22.9691447,"Turn":20,"DayValue":"一,二,四,六","RecycleDate":"一,四"},{"StopId":7072,"StopName":"文化街二段31號","ScheduleTime":"17:24","EstimateTime":"","CarInfo":"","Lon":120.2936155,"Lat":22.9691844,"Turn":21,"DayValue":"一,二,四,六","RecycleDate":"一,四"},{"StopId":7073,"StopName":"文化街二段53巷內","ScheduleTime":"17:25","EstimateTime":"","CarInfo":"","Lon":120.2934062,"Lat":22.9691704,"Turn":22,"DayValue":"一,二,四,六","RecycleDate":"一,四"},{"StopId":7074,"StopName":"文化街二段70號","ScheduleTime":"17:26","EstimateTime":"","CarInfo":"","Lon":120.2910653,"Lat":22.9701748,"Turn":23,"DayValue":"一,二,四,六","RecycleDate":"一,四"},{"StopId":7075,"StopName":"國光街117號","ScheduleTime":"17:27","EstimateTime":"","CarInfo":"","Lon":120.2913614,"Lat":22.9697173,"Turn":24,"DayValue":"一,二,四,六","RecycleDate":"一,四"},{"StopId":7076,"StopName":"民權三街63號","ScheduleTime":"17:28","EstimateTime":"","CarInfo":"","Lon":120.2893959,"Lat":22.9695002,"Turn":25,"DayValue":"一,二,四,六","RecycleDate":"一,四"},{"StopId":7077,"StopName":"民權三街110號","ScheduleTime":"17:29","EstimateTime":"","CarInfo":"","Lon":120.2905821,"Lat":22.9694063,"Turn":26,"DayValue":"一,二,四,六","RecycleDate":"一,四"},{"StopId":7078,"StopName":"民權三街15號","ScheduleTime":"17:29","EstimateTime":"","CarInfo":"","Lon":120.2899634,"Lat":22.9694514,"Turn":27,"DayValue":"一,二,四,六","RecycleDate":"一,四"},{"StopId":7079,"StopName":"文化五街19巷口","ScheduleTime":"17:30","EstimateTime":"","CarInfo":"","Lon":120.28921,"Lat":22.970116,"Turn":28,"DayValue":"一,二,四,六","RecycleDate":"一,四"},{"StopId":7080,"StopName":"文化街二段139巷口","ScheduleTime":"17:33","EstimateTime":"","CarInfo":"","Lon":120.289479,"Lat":22.970653,"Turn":29,"DayValue":"一,二,四,六","RecycleDate":"一,四"},{"StopId":7081,"StopName":"文化街二段113號","ScheduleTime":"17:35","EstimateTime":"","CarInfo":"","Lon":120.2905835,"Lat":22.9703564,"Turn":30,"DayValue":"一,二,四,六","RecycleDate":"一,四"},{"StopId":7082,"StopName":"文化街二段121巷12號","ScheduleTime":"17:37","EstimateTime":"","CarInfo":"","Lon":120.2900487,"Lat":22.9699648,"Turn":31,"DayValue":"一,二,四,六","RecycleDate":"一,四"},{"StopId":7083,"StopName":"文化街二段121巷7弄18號","ScheduleTime":"17:39","EstimateTime":"","CarInfo":"","Lon":120.2901795,"Lat":22.9699347,"Turn":32,"DayValue":"一,二,四,六","RecycleDate":"一,四"},{"StopId":7084,"StopName":"文化街二段75號","ScheduleTime":"17:41","EstimateTime":"","CarInfo":"","Lon":120.2910061,"Lat":22.9701971,"Turn":33,"DayValue":"一,二,四,六","RecycleDate":"一,四"},{"StopId":7085,"StopName":"國光街143巷口、巷內","ScheduleTime":"17:43","EstimateTime":"","CarInfo":"","Lon":120.2883342,"Lat":22.9684418,"Turn":34,"DayValue":"一,二,四,六","RecycleDate":"一,四"},{"StopId":7086,"StopName":"民權一街38巷口","ScheduleTime":"17:45","EstimateTime":"","CarInfo":"","Lon":120.2897465,"Lat":22.9719327,"Turn":35,"DayValue":"一,二,四,六","RecycleDate":"一,四"},{"StopId":7087,"StopName":"文化北街＆國光街巷口","ScheduleTime":"17:47","EstimateTime":"","CarInfo":"","Lon":120.2884479,"Lat":22.9725442,"Turn":36,"DayValue":"一,二,四,六","RecycleDate":"一,四"},{"StopId":7088,"StopName":"文化北街16號","ScheduleTime":"17:49","EstimateTime":"","CarInfo":"","Lon":120.2921012,"Lat":22.9724333,"Turn":37,"DayValue":"一,二,四,六","RecycleDate":"一,四"},{"StopId":7089,"StopName":"文化北街76號","ScheduleTime":"17:50","EstimateTime":"","CarInfo":"","Lon":120.2909476,"Lat":22.9724931,"Turn":38,"DayValue":"一,二,四,六","RecycleDate":"一,四"},{"StopId":7090,"StopName":"文化北一街61號","ScheduleTime":"17:52","EstimateTime":"","CarInfo":"","Lon":120.2908945,"Lat":22.9728901,"Turn":39,"DayValue":"一,二,四,六","RecycleDate":"一,四"},{"StopId":7091,"StopName":"文化北一街35號","ScheduleTime":"17:54","EstimateTime":"","CarInfo":"","Lon":120.2914128,"Lat":22.9728712,"Turn":40,"DayValue":"一,二,四,六","RecycleDate":"一,四"},{"StopId":7092,"StopName":"文化北一街5號","ScheduleTime":"17:56","EstimateTime":"","CarInfo":"","Lon":120.2917054,"Lat":22.9728722,"Turn":41,"DayValue":"一,二,四,六","RecycleDate":"一,四"},{"StopId":7093,"StopName":"大德路193巷23號","ScheduleTime":"17:58","EstimateTime":"","CarInfo":"","Lon":120.2915957,"Lat":22.9731198,"Turn":42,"DayValue":"一,二,四,六","RecycleDate":"一,四"},{"StopId":7094,"StopName":"大德路193巷8號","ScheduleTime":"18:00","EstimateTime":"","CarInfo":"","Lon":120.2921503,"Lat":22.9730312,"Turn":43,"DayValue":"一,二,四,六","RecycleDate":"一,四"},{"StopId":7095,"StopName":"文化北街92號","ScheduleTime":"18:02","EstimateTime":"","CarInfo":"","Lon":120.2904626,"Lat":22.9725021,"Turn":44,"DayValue":"一,二,四,六","RecycleDate":"一,四"},{"StopId":7096,"StopName":"文化北街120號","ScheduleTime":"18:03","EstimateTime":"","CarInfo":"","Lon":120.2896994,"Lat":22.9724734,"Turn":45,"DayValue":"一,二,四,六","RecycleDate":"一,四"},{"StopId":7097,"StopName":"文化北街(巨光幼稚園前)","ScheduleTime":"18:04","EstimateTime":"","CarInfo":"","Lon":120.2887621,"Lat":22.9725778,"Turn":46,"DayValue":"一,二,四,六","RecycleDate":"一,四"},{"StopId":7098,"StopName":"民權北路210號","ScheduleTime":"18:05","EstimateTime":"","CarInfo":"","Lon":120.2882844,"Lat":22.972092,"Turn":47,"DayValue":"一,二,四,六","RecycleDate":"一,四"},{"StopId":7099,"StopName":"大德路321號","ScheduleTime":"18:55","EstimateTime":"","CarInfo":"","Lon":120.287688,"Lat":22.9737261,"Turn":48,"DayValue":"一,二,四,六","RecycleDate":"一,四"},{"StopId":7100,"StopName":"大德路253號","ScheduleTime":"18:57","EstimateTime":"","CarInfo":"","Lon":120.28941,"Lat":22.9735856,"Turn":49,"DayValue":"一,二,四,六","RecycleDate":"一,四"},{"StopId":7101,"StopName":"大德路237巷口","ScheduleTime":"18:59","EstimateTime":"","CarInfo":"","Lon":120.2896887,"Lat":22.9735557,"Turn":50,"DayValue":"一,二,四,六","RecycleDate":"一,四"},{"StopId":7102,"StopName":"民族北街207號","ScheduleTime":"19:01","EstimateTime":"","CarInfo":"","Lon":120.2925122,"Lat":22.9696606,"Turn":51,"DayValue":"一,二,四,六","RecycleDate":"一,四"},{"StopId":7103,"StopName":"民族北街155號","ScheduleTime":"19:03","EstimateTime":"","CarInfo":"","Lon":120.2924965,"Lat":22.9695154,"Turn":52,"DayValue":"一,二,四,六","RecycleDate":"一,四"},{"StopId":7104,"StopName":"文化三街18號","ScheduleTime":"19:05","EstimateTime":"","CarInfo":"","Lon":120.2902121,"Lat":22.9710657,"Turn":53,"DayValue":"一,二,四,六","RecycleDate":"一,四"},{"StopId":7105,"StopName":"文化三街60號","ScheduleTime":"19:07","EstimateTime":"","CarInfo":"","Lon":120.2902259,"Lat":22.9725893,"Turn":54,"DayValue":"一,二,四,六","RecycleDate":"一,四"},{"StopId":7106,"StopName":"民權一街45號","ScheduleTime":"19:09","EstimateTime":"","CarInfo":"","Lon":120.2897465,"Lat":22.9719327,"Turn":55,"DayValue":"一,二,四,六","RecycleDate":"一,四"},{"StopId":7107,"StopName":"民權一街25號","ScheduleTime":"19:11","EstimateTime":"","CarInfo":"","Lon":120.2893008,"Lat":22.971943,"Turn":56,"DayValue":"一,二,四,六","RecycleDate":"一,四"},{"StopId":7108,"StopName":"文化北二街80巷口","ScheduleTime":"19:13","EstimateTime":"","CarInfo":"","Lon":120.2890502,"Lat":22.9730277,"Turn":57,"DayValue":"一,二,四,六","RecycleDate":"一,四"},{"StopId":7109,"StopName":"文化北二街5號","ScheduleTime":"19:15","EstimateTime":"","CarInfo":"","Lon":120.2900921,"Lat":22.9728723,"Turn":58,"DayValue":"一,二,四,六","RecycleDate":"一,四"},{"StopId":7110,"StopName":"民權二街17號","ScheduleTime":"19:20","EstimateTime":"","CarInfo":"","Lon":120.2877089,"Lat":22.9730091,"Turn":59,"DayValue":"一,二,四,六","RecycleDate":"一,四"},{"StopId":7111,"StopName":"民權二街30號","ScheduleTime":"19:22","EstimateTime":"","CarInfo":"","Lon":120.2876781,"Lat":22.9729267,"Turn":60,"DayValue":"一,二,四,六","RecycleDate":"一,四"},{"StopId":7112,"StopName":"民權北路175號","ScheduleTime":"19:24","EstimateTime":"","CarInfo":"","Lon":120.2882775,"Lat":22.9725973,"Turn":61,"DayValue":"一,二,四,六","RecycleDate":"一,四"},{"StopId":7113,"StopName":"民權北路155號","ScheduleTime":"19:26","EstimateTime":"","CarInfo":"","Lon":120.2882843,"Lat":22.972103,"Turn":62,"DayValue":"一,二,四,六","RecycleDate":"一,四"},{"StopId":7114,"StopName":"民權北路107號","ScheduleTime":"19:28","EstimateTime":"","CarInfo":"","Lon":120.2880642,"Lat":22.9699612,"Turn":63,"DayValue":"一,二,四,六","RecycleDate":"一,四"},{"StopId":7115,"StopName":"民權北路53號","ScheduleTime":"19:30","EstimateTime":"","CarInfo":"","Lon":120.287959,"Lat":22.968879,"Turn":64,"DayValue":"一,二,四,六","RecycleDate":"一,四"},{"StopId":7116,"StopName":"民權北路22號","ScheduleTime":"19:32","EstimateTime":"","CarInfo":"","Lon":120.287879,"Lat":22.96716,"Turn":65,"DayValue":"一,二,四,六","RecycleDate":"一,四"},{"StopId":7117,"StopName":"國光街20號","ScheduleTime":"19:34","EstimateTime":"","CarInfo":"","Lon":120.288599,"Lat":22.968335,"Turn":66,"DayValue":"一,二,四,六","RecycleDate":"一,四"},{"StopId":7118,"StopName":"國光街59號(後市里辦公室)","ScheduleTime":"19:35","EstimateTime":"","CarInfo":"","Lon":120.2897566,"Lat":22.9683509,"Turn":67,"DayValue":"一,二,四,六","RecycleDate":"一,四"},{"StopId":7119,"StopName":"國光街98巷內","ScheduleTime":"19:37","EstimateTime":"","CarInfo":"","Lon":120.2907094,"Lat":22.9682557,"Turn":68,"DayValue":"一,二,四,六","RecycleDate":"一,四"},{"StopId":7120,"StopName":"中山八街46巷口","ScheduleTime":"19:39","EstimateTime":"","CarInfo":"","Lon":120.290337,"Lat":22.968968,"Turn":69,"DayValue":"一,二,四,六","RecycleDate":"一,四"},{"StopId":7121,"StopName":"民權六街19巷口","ScheduleTime":"19:41","EstimateTime":"","CarInfo":"","Lon":120.2876003,"Lat":22.9696274,"Turn":70,"DayValue":"一,二,四,六","RecycleDate":"一,四"},{"StopId":7122,"StopName":"民權北路61巷9弄2號","ScheduleTime":"19:43","EstimateTime":"","CarInfo":"","Lon":120.287879,"Lat":22.96716,"Turn":71,"DayValue":"一,二,四,六","RecycleDate":"一,四"},{"StopId":7123,"StopName":"民權八街30巷口","ScheduleTime":"19:45","EstimateTime":"","CarInfo":"","Lon":120.2854581,"Lat":22.969681,"Turn":72,"DayValue":"一,二,四,六","RecycleDate":"一,四"},{"StopId":7124,"StopName":"民權八街53巷口","ScheduleTime":"19:47","EstimateTime":"","CarInfo":"","Lon":120.2863894,"Lat":22.9685663,"Turn":73,"DayValue":"一,二,四,六","RecycleDate":"一,四"},{"StopId":7125,"StopName":"中山路三段100巷11號","ScheduleTime":"19:48","EstimateTime":"","CarInfo":"","Lon":120.2858057,"Lat":22.9684506,"Turn":74,"DayValue":"一,二,四,六","RecycleDate":"一,四"},{"StopId":7126,"StopName":"民權北路61巷70號","ScheduleTime":"19:49","EstimateTime":"","CarInfo":"","Lon":120.286166,"Lat":22.9693,"Turn":75,"DayValue":"一,二,四,六","RecycleDate":"一,四"},{"StopId":7127,"StopName":"民權六街52巷口","ScheduleTime":"19:50","EstimateTime":"","CarInfo":"","Lon":120.2868014,"Lat":22.96967,"Turn":76,"DayValue":"一,二,四,六","RecycleDate":"一,四"},{"StopId":7128,"StopName":"文化六街口、街內","ScheduleTime":"19:55","EstimateTime":"","CarInfo":"","Lon":120.2862723,"Lat":22.9713328,"Turn":77,"DayValue":"一,二,四,六","RecycleDate":"一,四"},{"StopId":7129,"StopName":"文化街三段61巷口、巷內","ScheduleTime":"19:57","EstimateTime":"","CarInfo":"","Lon":120.287921,"Lat":22.970957,"Turn":78,"DayValue":"一,二,四,六","RecycleDate":"一,四"},{"StopId":7130,"StopName":"文化街三段18巷內","ScheduleTime":"20:00","EstimateTime":"","CarInfo":"","Lon":120.288012,"Lat":22.970947,"Turn":79,"DayValue":"一,二,四,六","RecycleDate":"一,四"}],"CarData":[],"RouteId":303,"RouteName":"歸仁-5","RouteInfo":"大通一街26號~文化街三段18巷內","IsWork":true}]